minify_html-0.18.0.dist-info/METADATA
minify_html-0.18.0.dist-info/WHEEL
minify_html.libs/libgcc_s-98a1ef30.so.1
minify_html/__init__.py
minify_html/__init__.pyi
minify_html/minify_html.cpython-39-x86_64-linux-gnu.so
minify_html/py.typed
minify_html-0.18.0.dist-info/RECORD
